lesser.py
lesser-0.1.1.dist-info/METADATA
lesser-0.1.1.dist-info/WHEEL
lesser-0.1.1.dist-info/top_level.txt
lesser-0.1.1.dist-info/RECORD
