Metadata-Version: 2.1
Name: lesser
Version: 0.1.1
Summary: Simple version of pandas
Author: wuthefwasthat
